pyirf/__init__.py
pyirf/_version.py
pyirf/binning.py
pyirf/compat.py
pyirf/conftest.py
pyirf/coordinates.py
pyirf/cut_optimization.py
pyirf/cuts.py
pyirf/exceptions.py
pyirf/gammapy.py
pyirf/sensitivity.py
pyirf/simulations.py
pyirf/spectral.py
pyirf/statistics.py
pyirf/utils.py
pyirf/version.py
pyirf/benchmarks/__init__.py
pyirf/benchmarks/angular_resolution.py
pyirf/benchmarks/energy_bias_resolution.py
pyirf/benchmarks/tests/__init__.py
pyirf/benchmarks/tests/test_angular_resolution.py
pyirf/benchmarks/tests/test_bias_resolution.py
pyirf/interpolation/__init__.py
pyirf/interpolation/base_extrapolators.py
pyirf/interpolation/base_interpolators.py
pyirf/interpolation/component_estimators.py
pyirf/interpolation/griddata_interpolator.py
pyirf/interpolation/moment_morph_interpolator.py
pyirf/interpolation/nearest_neighbor_searcher.py
pyirf/interpolation/nearest_simplex_extrapolator.py
pyirf/interpolation/quantile_interpolator.py
pyirf/interpolation/utils.py
pyirf/interpolation/visible_edges_extrapolator.py
pyirf/interpolation/tests/__init__.py
pyirf/interpolation/tests/test_base_extrapolators.py
pyirf/interpolation/tests/test_base_interpolators.py
pyirf/interpolation/tests/test_component_estimator_base_classes.py
pyirf/interpolation/tests/test_component_estimator_specific_classes.py
pyirf/interpolation/tests/test_griddata_interpolator.py
pyirf/interpolation/tests/test_moment_morph_interpolator.py
pyirf/interpolation/tests/test_nearest_neighbor_searcher.py
pyirf/interpolation/tests/test_nearest_simplex_extrapolator.py
pyirf/interpolation/tests/test_quantile_interpolator.py
pyirf/interpolation/tests/test_utils.py
pyirf/interpolation/tests/test_visible_edges_extrapolator.py
pyirf/io/__init__.py
pyirf/io/eventdisplay.py
pyirf/io/gadf.py
pyirf/io/tests/__init__.py
pyirf/io/tests/test_gadf.py
pyirf/irf/__init__.py
pyirf/irf/background.py
pyirf/irf/effective_area.py
pyirf/irf/energy_dispersion.py
pyirf/irf/psf.py
pyirf/irf/tests/__init__.py
pyirf/irf/tests/test_background.py
pyirf-0.13.0.dist-info/licenses/LICENSE
pyirf-0.13.0.dist-info/METADATA
pyirf-0.13.0.dist-info/WHEEL
pyirf-0.13.0.dist-info/top_level.txt
pyirf-0.13.0.dist-info/RECORD
