Metadata-Version: 2.4
Name: pyirf
Version: 0.13.0
Summary: A python library to calculate IACT IRFs and Sensitivities
Author-email: "CTA Consortium, Analysis and Simulation Working Group" <maximilian.linhoff@tu-dortmund.de>
License-Expression: MIT
Project-URL: Homepage, https://github.com/cta-observatory/pyirf
Project-URL: Bug Tracker, https://github.com/cta-observatory/pyirf/issues
Project-URL: Documentation, https://cta-observatory.github.io/pyirf
Project-URL: Source Code, https://github.com/cta-observatory/pyirf
Classifier: Development Status :: 4 - Beta
Classifier: Intended Audience :: Science/Research
Classifier: Topic :: Scientific/Engineering :: Astronomy
Classifier: Topic :: Scientific/Engineering :: Physics
Classifier: Programming Language :: Python :: 3 :: Only
Classifier: Programming Language :: Python :: 3.10
Classifier: Programming Language :: Python :: 3.11
Classifier: Programming Language :: Python :: 3.12
Classifier: Programming Language :: Python :: 3.13
Requires-Python: >=3.10
License-File: LICENSE
Requires-Dist: astropy<8.0.0a0,>=5.3
Requires-Dist: numpy>=1.21
Requires-Dist: scipy
Requires-Dist: tqdm
Requires-Dist: packaging
Provides-Extra: gammapy
Requires-Dist: gammapy~=1.0; extra == "gammapy"
Provides-Extra: docs
Requires-Dist: sphinx; extra == "docs"
Requires-Dist: sphinx_rtd_theme; extra == "docs"
Requires-Dist: sphinx_automodapi; extra == "docs"
Requires-Dist: numpydoc; extra == "docs"
Requires-Dist: nbsphinx; extra == "docs"
Requires-Dist: notebook; extra == "docs"
Requires-Dist: tables; extra == "docs"
Requires-Dist: towncrier; extra == "docs"
Requires-Dist: pyirf[gammapy]; extra == "docs"
Provides-Extra: tests
Requires-Dist: pytest; extra == "tests"
Requires-Dist: pytest-cov; extra == "tests"
Requires-Dist: ogadf-schema~=0.2.3; extra == "tests"
Requires-Dist: pyirf[gammapy]; extra == "tests"
Provides-Extra: dev
Requires-Dist: setuptools_scm; extra == "dev"
Provides-Extra: all
Requires-Dist: pyirf[dev,docs,tests]; extra == "all"
Dynamic: license-file
